pygi.py
pygi-1.0.3.dist-info/DESCRIPTION.rst
pygi-1.0.3.dist-info/METADATA
pygi-1.0.3.dist-info/RECORD
pygi-1.0.3.dist-info/WHEEL
pygi-1.0.3.dist-info/entry_points.txt
pygi-1.0.3.dist-info/metadata.json
pygi-1.0.3.dist-info/top_level.txt
